{
    "keep": {
        "days": false,
        "amount": 2
    },
    "auditLog": "src\\dailylog\\user-error-log\\.02112c18f5f5678008c5d8a97d47ee4cd59270af-audit.json",
    "files": [
        {
            "date": 1668440397693,
            "name": "src\\dailylog\\user-error-log\\user-info-2022-11-14-22-09.log",
            "hash": "9e52a062c6b1eb66c84b9ddf13d1a6175e8fe4d5ad43825b09f3bbe45f76a84d"
        },
        {
            "date": 1668489644436,
            "name": "src\\dailylog\\user-error-log\\user-info-2022-11-15-11-50.log",
            "hash": "c64ce7a3ce7b6e330b24c770d34dfdec113a2f1c8b5c82dc17ed4f4b936ca6b4"
        }
    ],
    "hashType": "sha256"
}